CryptoPho/__init__.py
CryptoPho-0.0.0.2.dist-info/LICENSE
CryptoPho-0.0.0.2.dist-info/METADATA
CryptoPho-0.0.0.2.dist-info/WHEEL
CryptoPho-0.0.0.2.dist-info/top_level.txt
CryptoPho-0.0.0.2.dist-info/RECORD
