Metadata-Version: 2.1
Name: CryptoPho
Version: 0.0.0.2
Summary: A random project
Home-page: https://github.com/ThePhoenix78/CryptoPho
Author: ThePhoenix78
Author-email: thephoenix788@gmail.com
License: MIT
Download-URL: https://github.com/ThePhoenix78/CryptoPho/tarball/master
Keywords: python,python3,python3.x,ThePhoenix78
Platform: UNKNOWN
Classifier: Programming Language :: Python :: 3
Classifier: License :: OSI Approved :: MIT License
Classifier: Operating System :: OS Independent
Requires-Dist: setuptools
